aiolivisi/__init__.py
aiolivisi/aiolivisi.py
aiolivisi/const.py
aiolivisi/errors.py
aiolivisi/livisi_event.py
aiolivisi/websocket.py
aiolivisi-0.0.19.dist-info/LICENSE
aiolivisi-0.0.19.dist-info/METADATA
aiolivisi-0.0.19.dist-info/WHEEL
aiolivisi-0.0.19.dist-info/top_level.txt
aiolivisi-0.0.19.dist-info/RECORD
