Metadata-Version: 2.1
Name: aiolivisi
Version: 0.0.19
Summary: Python module to communicate with LIVISI Smart Home Controllers.
Home-page: https://github.com/StefanIacobLivisi/aiolivisi
Author: Stefan Iacob
Author-email: stefan.iacob.extern@livisi.de
License: Apache License 2.0
Platform: any
Classifier: Programming Language :: Python :: 3
Classifier: Operating System :: OS Independent
Classifier: Topic :: Software Development :: Libraries :: Python Modules
License-File: LICENSE
Requires-Dist: aiohttp
Requires-Dist: websockets
Requires-Dist: pydantic
